{"cameraMode":{"drawMode":0,"name":"Shaded","section":"Shading Mode"},"sceneLighting":false,"audioPlay":false,"sceneViewState":{"m_AlwaysRefresh":false,"showFog":true,"showSkybox":false,"showFlares":true,"showImageEffects":true,"showParticleSystems":true,"showVisualEffectGraphs":true,"m_FxEnabled":true},"in2DMode":false,"pivot":{"x":2.6813814640045168,"y":-0.8573439121246338,"z":-15.671236991882325},"rotation":{"x":0.3479439616203308,"y":-0.5071037411689758,"z":0.23437142372131349,"w":0.7529402375221252},"size":2.787736415863037,"orthographic":false}